brunns/__init__.py
brunns/py.typed
brunns/matchers/__init__.py
brunns/matchers/bytestring.py
brunns/matchers/data.py
brunns/matchers/datetime.py
brunns/matchers/dbapi.py
brunns/matchers/html.py
brunns/matchers/matcher.py
brunns/matchers/meta.py
brunns/matchers/mock.py
brunns/matchers/object.py
brunns/matchers/response.py
brunns/matchers/rss.py
brunns/matchers/smtp.py
brunns/matchers/url.py
brunns/matchers/utils.py
brunns/matchers/werkzeug.py
brunns_matchers-2.10.0.dist-info/licenses/LICENSE
brunns_matchers-2.10.0.dist-info/METADATA
brunns_matchers-2.10.0.dist-info/WHEEL
brunns_matchers-2.10.0.dist-info/top_level.txt
brunns_matchers-2.10.0.dist-info/RECORD
