Metadata-Version: 2.4
Name: brunns-matchers
Version: 2.10.0
Summary: Custom PyHamcrest matchers
Home-page: https://github.com/brunns/brunns-matchers/
Author: Simon Brunning
Author-email: simon@brunningonline.net
Classifier: Development Status :: 5 - Production/Stable
Classifier: Intended Audience :: Developers
Classifier: License :: OSI Approved :: MIT License
Classifier: Operating System :: OS Independent
Classifier: Programming Language :: Python
Classifier: Programming Language :: Python :: 3
Classifier: Programming Language :: Python :: 3.9
Classifier: Programming Language :: Python :: 3.10
Classifier: Programming Language :: Python :: 3.11
Classifier: Programming Language :: Python :: 3.12
Classifier: Programming Language :: Python :: 3.13
Classifier: Programming Language :: Python :: Implementation :: PyPy
Classifier: Topic :: Software Development :: Testing
Requires-Python: >=3.9
License-File: LICENSE
Requires-Dist: pyhamcrest>=2.0
Requires-Dist: Deprecated>=1.2
Requires-Dist: brunns-row>=2.0
Requires-Dist: beautifulsoup4>=4.0
Requires-Dist: requests>=2.0
Requires-Dist: httpx>=0.28
Requires-Dist: yarl>=1.9
Requires-Dist: furl>=2.0
Requires-Dist: Werkzeug>=2.0
Requires-Dist: feedparser>=6.0
Dynamic: author
Dynamic: author-email
Dynamic: classifier
Dynamic: description
Dynamic: description-content-type
Dynamic: home-page
Dynamic: license-file
Dynamic: requires-dist
Dynamic: requires-python
Dynamic: summary
